pyramid_openapi3/__init__.py
pyramid_openapi3/exceptions.py
pyramid_openapi3/py.typed
pyramid_openapi3/static/index.html
pyramid_openapi3/static/oauth2-redirect.html
pyramid_openapi3/tween.py
pyramid_openapi3/wrappers.py
pyramid_openapi3-0.21.0.dist-info/LICENSE
pyramid_openapi3-0.21.0.dist-info/METADATA
pyramid_openapi3-0.21.0.dist-info/WHEEL
pyramid_openapi3-0.21.0.dist-info/RECORD
