Metadata-Version: 2.1
Name: pyramid_openapi3
Version: 0.21.0
Summary: Pyramid addon for OpenAPI3 validation of requests and responses.
Home-page: https://github.com/Pylons/pyramid_openapi3
License: MIT
Keywords: pyramid,openapi3,openapi,rest,restful
Author: Neyts Zupan
Requires-Python: >=3.10,<4.0
Classifier: Development Status :: 4 - Beta
Classifier: Framework :: Pyramid
Classifier: Intended Audience :: Developers
Classifier: License :: OSI Approved :: MIT License
Classifier: Programming Language :: Python :: 3
Classifier: Programming Language :: Python :: 3.10
Classifier: Programming Language :: Python :: 3.11
Classifier: Programming Language :: Python :: 3.12
Classifier: Topic :: Internet :: WWW/HTTP
Classifier: Topic :: Software Development :: Libraries :: Python Modules
Requires-Dist: openapi-core (>=0.19.1)
Requires-Dist: pyramid (>=1.10.7)
Project-URL: Repository, https://github.com/Pylons/pyramid_openapi3
